mosyn/__init__.py
mosyn/__main__.py
mosyn/mosyn.py
mosyn/dict/spanish_dict.csv
mosyn/util/__init__.py
mosyn/util/eagles.py
mosyn/util/events.py
mosyn/util/format.py
mosyn/util/io.py
mosyn/util/labels.py
mosyn-1.1.0.dist-info/METADATA
mosyn-1.1.0.dist-info/RECORD
mosyn-1.1.0.dist-info/WHEEL
mosyn-1.1.0.dist-info/entry_points.txt
mosyn-1.1.0.dist-info/top_level.txt
