Metadata-Version: 2.1
Name: mosyn
Version: 1.1.0
Summary: A morphological dictionary tool.
Home-page: https://github.com/uagdataanalysis/mosynapi
Author: uagdataanalysis
Author-email: uagdataanalysis@gmail.com
License: UNKNOWN
Download-URL: https://github.com/uagdataanalysis/mosynapi/tarball/1.1.0
Project-URL: Bug Reports, https://github.com/uagdataanalysis/mosynapi/issues
Project-URL: Source, https://github.com/uagdataanalysis/mosynapi/
Keywords: dictionary,morphological,analysis
Platform: UNKNOWN
Classifier: Programming Language :: Python :: 3
Classifier: License :: Other/Proprietary License
Classifier: Operating System :: OS Independent
Requires-Dist: nltk (>=3.0)
